{
  "url": "https://mykitchen101en.com/baked-mini-egg-sponge-cakes/",
  "name": "Cute Baked Mini Egg Sponge Cakes- Great for Any Occasion - MyKitchen101en.com",
  "description": "Baked mini egg sponge cakes, a traditional food that kids love. Mini cupcakes with rich egg fragrance made with just a few simple ingredients. These mini",
  "inLanguage": "en-US",
  "image": [
    {
      "url": "https://mykitchen101en.com/wp-content/uploads/2020/11/mini-baked-egg-sponge-cake-mykitchen101en-feature1.jpg"
    }
  ],
  "publisher": {
    "name": "MyKitchen101en.com",
    "url": "https://mykitchen101en.com"
  }
}